LICENSE
README.md
setup.cfg
setup.py
asyncio_requests/__init__.py
asyncio_requests/asyncio_request.py
asyncio_requests.egg-info/PKG-INFO
asyncio_requests.egg-info/SOURCES.txt
asyncio_requests.egg-info/dependency_links.txt
asyncio_requests.egg-info/requires.txt
asyncio_requests.egg-info/top_level.txt
asyncio_requests/helpers/__init__.py
asyncio_requests/helpers/common/__init__.py
asyncio_requests/helpers/common/date_helper.py
asyncio_requests/helpers/common/file_helper.py
asyncio_requests/helpers/internal/__init__.py
asyncio_requests/helpers/internal/circuit_breaker_helper.py
asyncio_requests/helpers/internal/filters_helper.py
asyncio_requests/helpers/internal/request_helper.py
asyncio_requests/helpers/internal/response_helper.py
asyncio_requests/logic/__init__.py
asyncio_requests/logic/ftp.py
asyncio_requests/logic/http.py
asyncio_requests/logic/sftp.py
asyncio_requests/logic/soap.py
asyncio_requests/utils/__init__.py
asyncio_requests/utils/constants.py
asyncio_requests/utils/exceptions.py
asyncio_requests/utils/http_file_config.py
asyncio_requests/utils/request_tracer.py