Metadata-Version: 2.1
Name: asyncio-requests
Version: 2.7.1
Summary: Any microservice will be able to use the “asyncio_requests” can make an async request(HTTP/SOAP/XML/FTP/redis) with the given payload to given address
Home-page: https://github.com/gofynd/asyncio-requests
Author: Arjunsingh Yadav, Manish Magnani, Devesh Ratthour
Author-email: arjunsinghyadav@fynd.com, manishmagnani@gofynd.com
License: MIT
Download-URL: https://github.com/gofynd/aio-requests/archive/refs/tags/v2.7.1.tar.gz
Platform: UNKNOWN
Classifier: Development Status :: 5 - Production/Stable
Classifier: Intended Audience :: Developers
Classifier: Topic :: Software Development :: Build Tools
Classifier: License :: OSI Approved :: MIT License
Classifier: Programming Language :: Python :: 3.10
License-File: LICENSE
